[
  { "max": 10, "language": "Alignment Tongue" },
  { "max": 20, "language": "Chaos" },
  { "max": 25, "language": "Law" },
  { "max": 30, "language": "Neutrality" },
  { "max": 35, "language": "Language of the Sixteenth Aeon" },
  { "max": 38, "language": "Ancient Sarsounian" },
  { "max": 42, "language": "Angelic (a.k.a. Overworld)" },
  { "max": 46, "language": "Archveult" },
  { "max": 49, "language": "Busiaco" },
  { "max": 52, "language": "Castillion" },
  { "max": 57, "language": "Demonic (a.k.a. sub-world/underworld)" },
  { "max": 60, "language": "Dilk" },
  { "max": 63, "language": "Maot" },
  { "max": 66, "language": "Melantine" },
  { "max": 70, "language": "Minuscule" },
  { "max": 74, "language": "Old Naotic" },
  { "max": 75, "language": "Sahar" },
  { "max": 79, "language": "Sandestin" },
  { "max": 82, "language": "Saponid" },
  { "max": 89, "language": "Simiode" },
  { "max": 90, "language": "Sxyzyskzyik" },
  { "max": 91, "language": "Thawn" },
  { "max": 92, "language": "Tree-dwarf" },
  { "max": 94, "language": "Twastic" },
  { "max": 95, "language": "Twk-man" },
  { "max": 98, "language": "Deodand" },
  { "max": 99, "language": "Erb" },
  { "max": 100, "language": "Grue" }
]
